CHANGELOG.md
LICENSE
README.md
workplanner/__init__.py
workplanner/app.py
workplanner/cli.py
workplanner/const.py
workplanner/crud.py
workplanner/database.py
workplanner/errors.py
workplanner/fields.py
workplanner/filters.py
workplanner/logger.py
workplanner/main.py
workplanner/models.py
workplanner/resources.py
workplanner/service.py
workplanner/settings.py
workplanner/utils.py
workplanner-1.0.1.dist-info/entry_points.txt
workplanner-1.0.1.dist-info/LICENSE
workplanner-1.0.1.dist-info/WHEEL
workplanner-1.0.1.dist-info/METADATA
workplanner-1.0.1.dist-info/RECORD
